nacvi/__init__.py
nacvi/daviesbouldin_plus.py
nacvi/dunn33_plus.py
nacvi/grid_plus.py
nacvi/neighbourhoodratio_plus.py
nacvi/scorefunction_plus.py
nacvi/silhouette_plus.py
nacvi-0.1.0.dist-info/licenses/LICENSE
nacvi-0.1.0.dist-info/METADATA
nacvi-0.1.0.dist-info/WHEEL
nacvi-0.1.0.dist-info/top_level.txt
nacvi-0.1.0.dist-info/RECORD
