Metadata-Version: 2.4
Name: nacvi
Version: 0.1.0
Summary: Cluster Validity Indices for Noise-Aware Clusterings (e.g. DBSCAN)
Home-page: https://github.com/leaeb/noise-aware-cvi
Author: Lea Eileen Brauner
Author-email: le.brauner@ostfalia.de
License: GPL-3.0-or-later
Project-URL: Bug Tracker, https://github.com/leaeb/noise-aware-cvi/issues
Classifier: Programming Language :: Python :: 3
Classifier: License :: OSI Approved :: GNU General Public License v3 (GPLv3)
Classifier: Operating System :: OS Independent
Classifier: Intended Audience :: Science/Research
Classifier: Topic :: Scientific/Engineering :: Artificial Intelligence
Requires-Python: >=3.10
License-File: LICENSE
Requires-Dist: contourpy==1.3.2
Requires-Dist: cycler==0.12.1
Requires-Dist: fonttools==4.58.5
Requires-Dist: joblib==1.5.1
Requires-Dist: kiwisolver==1.4.8
Requires-Dist: numpy==2.3.1
Requires-Dist: packaging==25.0
Requires-Dist: pandas==2.3.1
Requires-Dist: pillow==11.3.0
Requires-Dist: pyparsing==3.2.3
Requires-Dist: python-dateutil==2.9.0.post0
Requires-Dist: pytz==2025.2
Requires-Dist: scikit-learn==1.7.0
Requires-Dist: scipy==1.16.0
Requires-Dist: six==1.17.0
Requires-Dist: threadpoolctl==3.6.0
Requires-Dist: tzdata==2025.2
Dynamic: license-file
